unxt/__init__.py
unxt/_version.py
unxt/_version.pyi
unxt/dims.py
unxt/py.typed
unxt/quantity.py
unxt/setup_package.py
unxt/units.py
unxt/unitsystems.py
unxt/_interop/__init__.py
unxt/_interop/optional_deps.py
unxt/_interop/unxt_interop_astropy/__init__.py
unxt/_interop/unxt_interop_astropy/custom_types.py
unxt/_interop/unxt_interop_astropy/dimensions.py
unxt/_interop/unxt_interop_astropy/quantity.py
unxt/_interop/unxt_interop_astropy/units.py
unxt/_interop/unxt_interop_gala/__init__.py
unxt/_interop/unxt_interop_gala/unitsystems.py
unxt/_interop/unxt_interop_mpl/__init__.py
unxt/_src/__init__.py
unxt/_src/dimensions.py
unxt/_src/experimental.py
unxt/_src/units.py
unxt/_src/utils.py
unxt/_src/quantity/__init__.py
unxt/_src/quantity/angle.py
unxt/_src/quantity/base.py
unxt/_src/quantity/base_angle.py
unxt/_src/quantity/base_parametric.py
unxt/_src/quantity/flag.py
unxt/_src/quantity/mixins.py
unxt/_src/quantity/quantity.py
unxt/_src/quantity/register_api.py
unxt/_src/quantity/register_conversions.py
unxt/_src/quantity/register_dispatches.py
unxt/_src/quantity/register_primitives.py
unxt/_src/quantity/static_quantity.py
unxt/_src/quantity/unchecked.py
unxt/_src/quantity/value.py
unxt/_src/unitsystems/__init__.py
unxt/_src/unitsystems/base.py
unxt/_src/unitsystems/builtin.py
unxt/_src/unitsystems/builtin_dimensions.py
unxt/_src/unitsystems/compare.py
unxt/_src/unitsystems/core.py
unxt/_src/unitsystems/flags.py
unxt/_src/unitsystems/realizations.py
unxt/_src/unitsystems/utils.py
unxt-1.10.3.dist-info/METADATA
unxt-1.10.3.dist-info/WHEEL
unxt-1.10.3.dist-info/licenses/LICENSE
unxt-1.10.3.dist-info/RECORD
