Metadata-Version: 2.4
Name: unxt
Version: 1.10.3
Summary: Quantities in JAX
Project-URL: Bug Tracker, https://github.com/GalacticDynamics/unxt/issues
Project-URL: Changelog, https://github.com/GalacticDynamics/unxt/releases
Project-URL: Discussions, https://github.com/GalacticDynamics/unxt/discussions
Project-URL: Homepage, https://github.com/GalacticDynamics/unxt
Author-email: GalacticDynamics <nstarman@users.noreply.github.com>, Nathaniel Starkman <nstarman@users.noreply.github.com>, Adrian Price-Whelan <adrianmpw@gmail.com>
License: BSD 3-Clause License
License-File: LICENSE
Classifier: Development Status :: 3 - Alpha
Classifier: Intended Audience :: Developers
Classifier: Intended Audience :: Science/Research
Classifier: License :: OSI Approved :: BSD License
Classifier: Operating System :: OS Independent
Classifier: Programming Language :: Python
Classifier: Programming Language :: Python :: 3
Classifier: Programming Language :: Python :: 3 :: Only
Classifier: Programming Language :: Python :: 3.11
Classifier: Programming Language :: Python :: 3.12
Classifier: Programming Language :: Python :: 3.13
Classifier: Topic :: Scientific/Engineering
Classifier: Typing :: Typed
Requires-Python: >=3.11
Requires-Dist: astropy>=7.0.0
Requires-Dist: dataclassish>=0.8.0
Requires-Dist: equinox>=0.13.2
Requires-Dist: is-annotated>=1.0
Requires-Dist: jax>=0.5.3
Requires-Dist: jaxlib>=0.5.3
Requires-Dist: jaxtyping>=0.3.3
Requires-Dist: optional-dependencies>=0.3.2
Requires-Dist: plum-dispatch>=2.5.7
Requires-Dist: quax-blocks>=0.4.0
Requires-Dist: quax>=0.2.1
Requires-Dist: quaxed>=0.10.2
Requires-Dist: unxt-api>=1.10.0
Requires-Dist: wadler-lindig>=0.1.5
Requires-Dist: xmmutablemap>=0.1
Requires-Dist: zeroth>=1.0.0
Provides-Extra: all
Requires-Dist: astropy>=6.0; extra == 'all'
Requires-Dist: gala>=1.8; extra == 'all'
Requires-Dist: matplotlib>=3.8; extra == 'all'
Requires-Dist: unxt-api; extra == 'all'
Requires-Dist: unxt-hypothesis; extra == 'all'
Provides-Extra: backend-astropy
Requires-Dist: astropy>=6.0; extra == 'backend-astropy'
Provides-Extra: cpu
Requires-Dist: jax[cpu]>=0.5.3; extra == 'cpu'
Provides-Extra: cuda
Requires-Dist: jax[cuda]>=0.5.3; extra == 'cuda'
Provides-Extra: cuda12
Requires-Dist: jax[cuda12]>=0.5.3; extra == 'cuda12'
Provides-Extra: cuda12-local
Requires-Dist: jax[cuda12-local]>=0.5.3; extra == 'cuda12-local'
Provides-Extra: interop-gala
Requires-Dist: gala>=1.8; extra == 'interop-gala'
Provides-Extra: interop-mpl
Requires-Dist: matplotlib>=3.8; extra == 'interop-mpl'
Provides-Extra: k8s
Requires-Dist: jax[k8s]>=0.5.3; extra == 'k8s'
Provides-Extra: workspace
Requires-Dist: unxt-api; extra == 'workspace'
Requires-Dist: unxt-hypothesis; extra == 'workspace'
